pyhemnet/__init__.py
pyhemnet/constants.py
pyhemnet/hemnet.py
pyhemnet/qasa.py
pyhemnet-0.3.0.dist-info/licenses/LICENSE
pyhemnet-0.3.0.dist-info/METADATA
pyhemnet-0.3.0.dist-info/WHEEL
pyhemnet-0.3.0.dist-info/top_level.txt
pyhemnet-0.3.0.dist-info/RECORD
