Metadata-Version: 2.4
Name: pyhemnet
Version: 0.3.0
Summary: A Python library for accessing Swedish real estate and rental property data from Hemnet.se and Qasa.se
Author-email: ningdp2012 <ningdp2012@example.com>
License: MIT
Project-URL: Repository, https://github.com/ningdp2012/pyhemnet
Keywords: hemnet,qasa,real estate,rental,sweden,property,housing,data
Classifier: Development Status :: 3 - Alpha
Classifier: Intended Audience :: Developers
Classifier: License :: OSI Approved :: MIT License
Classifier: Programming Language :: Python :: 3.10
Classifier: Programming Language :: Python :: 3.11
Classifier: Programming Language :: Python :: 3.12
Classifier: Topic :: Software Development :: Libraries :: Python Modules
Requires-Python: >=3.10
License-File: LICENSE
Requires-Dist: cloudscraper>=1.2.71
Requires-Dist: beautifulsoup4>=4.12.0
Requires-Dist: requests>=2.31.0
Provides-Extra: dev
Requires-Dist: pytest>=7.0.0; extra == "dev"
Requires-Dist: black>=23.0.0; extra == "dev"
Requires-Dist: flake8>=6.0.0; extra == "dev"
Dynamic: license-file
